bartons/__init__.py
bartons/config.py
bartons/dates.py
bartons/errors.py
bartons/freqs.py
bartons/model.py
bartons/prices.py
bartons/random.py
bartons/tickers.py
bartons/utils.py
bartons/polygon/__init__.py
bartons/polygon/engine.py
bartons/polygon/utils.py
bartons/tests/__init__.py
bartons/tests/test_bartons.py
bartons/tests/test_polygon.py
bartons/tests/test_random.py
bartons/tests/test_tiingo.py
bartons/tests/test_yahoo.py
bartons/tiingo/__init__.py
bartons/tiingo/engine.py
bartons/tiingo/utils.py
bartons/yahoo/__init__.py
bartons/yahoo/engine.py
bartons/yahoo/utils.py
bartons-0.0.1.dist-info/METADATA
bartons-0.0.1.dist-info/WHEEL
bartons-0.0.1.dist-info/entry_points.txt
bartons-0.0.1.dist-info/licenses/LICENSE.txt
bartons-0.0.1.dist-info/RECORD
